tasks_generator/__init__.py
tasks_generator/logarithms.py
tasks_generator/super_functions.py
tasks_generator-0.0.6.dist-info/LICENSE
tasks_generator-0.0.6.dist-info/METADATA
tasks_generator-0.0.6.dist-info/WHEEL
tasks_generator-0.0.6.dist-info/top_level.txt
tasks_generator-0.0.6.dist-info/RECORD
