Metadata-Version: 2.1
Name: tasks-generator
Version: 0.0.6
Summary: This module was written for education in math, by generating math tasks
Home-page: https://github.com/XxXDeathmatchXxX/tasks_generator.git
Author: Kirill Kudinov
License: MIT
Classifier: Programming Language :: Python
Classifier: Programming Language :: Python :: 3.9
Classifier: Topic :: Software Development :: Libraries :: Python Modules
License-File: LICENSE
